{
  "timestamp": "2025-12-04T08:00:37.805Z",
  "duration": 18.233,
  "successCount": 0,
  "totalCount": 1,
  "urls": [
    "http://localhost:3000/login"
  ],
  "config": {
    "urls": [
      "http://localhost:3000/login"
    ],
    "outputDir": "/Users/laichangcheng/Documents/文稿 - 来长城的MacBook Air/trae/L2C/slideboard-frontend/lighthouse-results",
    "chromeFlags": "--no-sandbox --headless --disable-gpu",
    "throttlingMethod": "simulate",
    "throttling": {
      "rttMs": 150,
      "throughputKbps": 1638.4,
      "cpuSlowdownMultiplier": 4
    }
  }
}